socservthread/__init__.py
socservthread/socservthread.py
socservthread-1.1.4.dist-info/LICENCE
socservthread-1.1.4.dist-info/METADATA
socservthread-1.1.4.dist-info/WHEEL
socservthread-1.1.4.dist-info/top_level.txt
socservthread-1.1.4.dist-info/RECORD
