Metadata-Version: 2.1
Name: socservthread
Version: 1.1.4
Summary: Serveur TCP socket
Author: Didier Orlandi
Author-email: didier.orlandi@wanadoo.fr
Classifier: Programming Language :: Python :: 3
Classifier: License :: OSI Approved :: MIT License
Classifier: Operating System :: OS Independent
Requires-Python: >=3.6
License-File: LICENCE
